{
  "taskListUID": "8e8c0fda-cd4d-11ed-afa1-0242ac120003",
  "taskListName": "Default Experiment",
  "communicationMethod": {
    "type": "MQTT",
    "host": "192.168.0.100",
    "port": "8080"
  },
  "loggingMethod": {
    "type": "local",
    "logFormater": "default",
    "logInOneLine": true
  },
  "stylingFile": "sadas.css",
  "taskStack": [
    [
      {
        "type": "CODE",
        "module": "ClearEventStorage",
        "props": { "functionInput": null, "runType": "onUnload" }
      },
      {
        "type": "CODE",
        "module": "SetTaskIndex",
        "props": { "functionInput": 1, "runType": "onLoad" }
      }
    ],

    [  
      {
        "type": "COMPONENT",
        "module": "MarenStartExperiment",
        "props": { 
          "operatorStationObjects":[
            {"label": "Operator 1", "metaKey": "Op1"},
            {"label": "Operator 2", "metaKey": "Op2"},
            {"label": "Supervisor", "metaKey": "SS"}
          ],
          "operatorMetaClick": {"function": "SetMetaData"},
          "onclick": [
            {"function": "SetExperimentStartTimestamp"},
            {"function": "SetTaskIndex"}
          ]
        }
      }
    ],
    
    [  
      {
        "type": "COMPONENT",
        "module": "SliderTask",
        "props": { 
          "questionLogKey": "Var1",
          "title": "Mental demand",
          "questionText": "How mentally demanding was the scenario?",
          "lowSliderText": "Very low",
          "highSliderText": "Very high",
          "buttonLabel":"Answer",
          "onclick": 
            {"function": "SetTaskIndex"}
        }
      }
    ],
    [  
      {
        "type": "COMPONENT",
        "module": "SliderTask",
        "props": { 
          "questionLogKey": "Var2",
          "title": "Physical demand",
          "questionText": "How physically demanding was the scenario?",
          "lowSliderText": "Very low",
          "highSliderText": "Very high",
          "buttonLabel":"Answer",
          "onclick": 
            {"function": "SetTaskIndex"}
        }
      }
    ],
    [  
      {
        "type": "COMPONENT",
        "module": "SliderTask",
        "props": { 
          "questionLogKey": "Var3",
          "title": "Temporal demand",
          "questionText": "How hurried or rushed was the pace of the scenario?",
          "lowSliderText": "Very low",
          "highSliderText": "Very high",
          "buttonLabel":"Answer",
          "onclick": 
            {"function": "SetTaskIndex"}
        }
      }
    ],
    [  
      {
        "type": "COMPONENT",
        "module": "SliderTask",
        "props": { 
          "questionLogKey": "Var4",
          "title": "Performance",
          "questionText": "How successful were you in accomplishing what you were asked to do?",
          "lowSliderText": "Perfect",
          "highSliderText": "Failure",
          "buttonLabel":"Answer",
          "onclick": 
            {"function": "SetTaskIndex"}
        }
      }
    ],
    [  
      {
        "type": "COMPONENT",
        "module": "SliderTask",
        "props": { 
          "questionLogKey": "Var5",
          "title": "Effort",
          "questionText": "How hard did you have to work to accomplish your level of performance?",
          "lowSliderText": "Very low",
          "highSliderText": "Very high",
          "buttonLabel":"Answer",
          "onclick": 
            {"function": "SetTaskIndex"}
        }
      }
    ],
    [  
      {
        "type": "COMPONENT",
        "module": "SliderTask",
        "props": { 
          "questionLogKey": "Var6",
          "title": "Frustration level",
          "questionText": "How insecure, discouraged, irritated, stressed, and annoyed were you?",
          "lowSliderText": "Very low",
          "highSliderText": "Very high",
          "buttonLabel":"Answer",
          "onclick": 
            {"function": "SetTaskIndex"}
        }
      }
    ],
    [  
      {
        "type": "COMPONENT",
        "module": "SliderTask",
        "props": { 
          "roleConditional":"Op1",
          "questionLogKey": "Var7",
          "title": "Mental demand",
          "questionText": "How mentally demanding was the scenario for <u>operator 1</u>?",
          "lowSliderText": "Very low",
          "highSliderText": "Very high",
          "buttonLabel":"Answer",
          "onclick": 
            {"function": "SetTaskIndex"}
        }
      }
    ],
    [  
      {
        "type": "COMPONENT",
        "module": "SliderTask",
        "props": { 
          "roleConditional":"Op2",
          "questionLogKey": "Var8",
          "title": "Mental demand",
          "questionText": "How mentally demanding was the scenario for <u>operator 2</u>?",
          "lowSliderText": "Very low",
          "highSliderText": "Very high",
          "buttonLabel":"Answer",
          "onclick": 
            {"function": "SetTaskIndex"}
        }
      }
    ],
    [  
      {
        "type": "COMPONENT",
        "module": "SliderTask",
        "props": { 
          "roleConditional":"SS",
          "questionLogKey": "Var9",
          "title": "Mental demand",
          "questionText": "How mentally demanding was the scenario for the <u>shift supervisor</u>?",
          "lowSliderText": "Very low",
          "highSliderText": "Very high",
          "buttonLabel":"Answer",
          "onclick": 
            {"function": "SetTaskIndex"}
        }
      }
    ],  

    [  
      {
        "type": "COMPONENT",
        "module": "MarenMultipleSliderTask",
        "props": { 
          "title": "How easy or difficult did you experience this scenario with respect to…",
          "questions":[
              {"questionLogKey": "Var10", "questionText": "Monitoring the SMR units"},
              {"questionLogKey": "Var11", "questionText": "Information processing demands"}
          ],
          "sliderProps": {
            "minValue": 1,
            "maxValue": 7,
            "defaultValue": 4,
            "step": 1,
            "displayTickNumbers": true
          },
          "lowSliderText": "Very easy",
          "highSliderText": "Very difficult",
          "buttonLabel":"Answer",
          "onclick": 
            {"function": "SetTaskIndex"}
        }
      }
    ],
    [  
      {
        "type": "COMPONENT",
        "module": "MarenMultipleSliderTask",
        "props": { 
          "title": "How easy or difficult did you experience this scenario with respect to…",
          "questions":[
              {"questionLogKey": "Var12", "questionText": "Time for planning, executing, and verifying the control tasks."},
              {"questionLogKey": "Var13", "questionText": "Extent of performing parallel tasks"}
          ],
          "sliderProps": {
            "minValue": 1,
            "maxValue": 7,
            "defaultValue": 4,
            "step": 1,
            "displayTickNumbers": true
          },
          "lowSliderText": "Very easy",
          "highSliderText": "Very difficult",
          "buttonLabel":"Answer",
          "onclick": 
            {"function": "SetTaskIndex"}
        }
      }
    ],
    [
      {
        "type": "COMPONENT",
        "module": "MarenMultipleSliderTask",
        "props": { 
          "title": "How easy or difficult did you experience this scenario with respect to...",
          "questions":[
              
              {"questionLogKey": "Var14", "questionText": "Extent of switching between tasks"},
              {"questionLogKey": "Var15", "questionText": "Extent of managing disturbances in multiple units"}
          ],
          "sliderProps": {
            "minValue": 1,
            "maxValue": 7,
            "defaultValue": 4,
            "step": 1,
            "displayTickNumbers": true
          },
          "lowSliderText": "Very easy",
          "highSliderText": "Very difficult",
          "buttonLabel":"Answer",
          "onclick": 
            {"function": "SetTaskIndex"}
        }
      }
    ],  

    [
      {
        "type": "COMPONENT",
        "module": "MarenMultipleSliderTask",
        "props": { 
          "title": "In this scenario,",
          "questions":[
              {"questionLogKey": "Var16", "questionText": "we maintained an overview of the SMR units"},
              {"questionLogKey": "Var17", "questionText": "we became aware of process deviations at an early stage"}
          ],
          "sliderProps": {
            "minValue": 1,
            "maxValue": 7,
            "defaultValue": 4,
            "step": 1,
            "displayTickNumbers": true
          },
          "lowSliderText": "Completely disagree",
          "highSliderText": "Completely agree",
          "buttonLabel":"Answer",
          "onclick": 
            {"function": "SetTaskIndex"}
        }
      }
    ],  
    [
      {
        "type": "COMPONENT",
        "module": "MarenMultipleSliderTask",
        "props": { 
          "title": "In this scenario,",
          "questions":[
              {"questionLogKey": "Var18", "questionText": "we made correct diagnoses of the process situation"},
              {"questionLogKey": "Var19", "questionText": "we determined appropriate strategies"}
          ],
          "sliderProps": {
            "minValue": 1,
            "maxValue": 7,
            "defaultValue": 4,
            "step": 1,
            "displayTickNumbers": true
          },
          "lowSliderText": "Completely disagree",
          "highSliderText": "Completely agree",
          "buttonLabel":"Answer",
          "onclick": 
            {"function": "SetTaskIndex"}
        }
      }
    ],  
    [
      {
        "type": "COMPONENT",
        "module": "MarenMultipleSliderTask",
        "props": { 
          "title": "In this scenario,",
          "questions":[

              {"questionLogKey": "Var20", "questionText": "we communicated effectively"},
              {"questionLogKey": "Var21", "questionText": "we performed peer checks and verifications when needed"}
          ],
          "sliderProps": {
            "minValue": 1,
            "maxValue": 7,
            "defaultValue": 4,
            "step": 1,
            "displayTickNumbers": true
          },
          "lowSliderText": "Completely disagree",
          "highSliderText": "Completely agree",
          "buttonLabel":"Answer",
          "onclick": 
            {"function": "SetTaskIndex"}
        }
      }
    ],  
    [
      {
        "type": "COMPONENT",
        "module": "MarenMultipleSliderTask",
        "props": { 
          "title": "In this scenario,",
          "questions":[
              {"questionLogKey": "Var22", "questionText": "we provided support to each other when needed"},
              {"questionLogKey": "Var23", "questionText": "we had the necessary resources to handle all tasks"}
          ],
          "sliderProps": {
            "minValue": 1,
            "maxValue": 7,
            "defaultValue": 4,
            "step": 1,
            "displayTickNumbers": true
          },
          "lowSliderText": "Completely disagree",
          "highSliderText": "Completely agree",
          "buttonLabel":"Answer",
          "onclick": 
            {"function": "SetTaskIndex"}
        }
      }
    ],  


    [  
      {
        "type": "COMPONENT",
        "module": "TextItemTask",
        "props": { 
          "label":"The experiment is over, please hand the device back to Halden staff.\n"
        }
      },
      {
        "type": "COMPONENT",
        "module": "Button",
        "props": { 
          "label":"Finish",
          "onclick": {"function": "SetTaskIndex"}
        }
      }
    ],     
    [
      {
        "type": "COMPONENT",
        "module": "TextItemTask",
        "props": { 
          "label":"Data file downloaded, refresh to start again."
        }
      },
      {
        "type": "CODE",
        "module": "DownloadLogEvents",
        "props": { 
          "runType": "onLoad",
          "functionInput": "eventLogSignal"
        }
      }
    ]
  ]
}
